{
  "name": "Bogster",
  "type": "dark",
  "colors": {
    "editor.background": "#141C24",
    "editor.foreground": "#e5ded6",
    "editor.lineHighlightBackground": "#13181e",
    "editor.selectionBackground": "#232d38",
    "editor.selectionHighlightBackground": "#313f4e40",
    "editor.findMatchBackground": "#dc7759",
    "editor.findMatchHighlightBackground": "#313f4e40",
    "editor.wordHighlightBackground": "#313f4e44",
    "editor.wordHighlightStrongBackground": "#313f4e66",
    "editorCursor.foreground": "#abb2bf",
    "editorLineNumber.foreground": "#415367",
    "editorLineNumber.activeForeground": "#e5ded6",
    "editorRuler.foreground": "#13181e",
    "editorWhitespace.foreground": "#313f4e",
    "editorIndentGuide.background1": "#232d38",
    "editorIndentGuide.activeBackground1": "#415367",
    
    "sideBar.background": "#13181e",
    "sideBar.foreground": "#e5ded6",
    "sideBar.border": "#13181e",
    "sideBarTitle.foreground": "#e5ded6",
    "sideBarSectionHeader.background": "#141C24",
    
    "list.activeSelectionBackground": "#313f4e",
    "list.activeSelectionForeground": "#e5ded6",
    "list.hoverBackground": "#232d38",
    "list.inactiveSelectionBackground": "#232d38",
    "list.focusBackground": "#313f4e",
    
    "statusBar.background": "#232d38",
    "statusBar.foreground": "#e5ded6",
    "statusBar.noFolderBackground": "#232d38",
    "statusBar.debuggingBackground": "#dc597f",
    "statusBar.debuggingForeground": "#141C24",
    
    "activityBar.background": "#13181e",
    "activityBar.foreground": "#e5ded6",
    "activityBar.border": "#13181e",
    "activityBarBadge.background": "#36b2d4",
    "activityBarBadge.foreground": "#141C24",
    
    "titleBar.activeBackground": "#141C24",
    "titleBar.activeForeground": "#e5ded6",
    "titleBar.inactiveBackground": "#141C24",
    "titleBar.inactiveForeground": "#c6b8ad",
    
    "tab.activeBackground": "#232d38",
    "tab.activeForeground": "#e5ded6",
    "tab.inactiveBackground": "#141C24",
    "tab.inactiveForeground": "#abb2bf",
    "tab.border": "#141C24",
    "editorGroupHeader.tabsBackground": "#141C24",
    "editorGroupHeader.tabsBorder": "#141C24",
    "editorGroup.border": "#141C24",
    
    "menu.background": "#232d38",
    "menu.foreground": "#e5ded6",
    "menu.selectionBackground": "#313f4e",
    
    "dropdown.background": "#232d38",
    "dropdown.foreground": "#e5ded6",
    "dropdown.border": "#232d38",
    
    "input.background": "#232d38",
    "input.foreground": "#e5ded6",
    "input.border": "#232d38",
    "input.placeholderForeground": "#abb2bf",
    "inputOption.activeBorder": "#36b2d4",
    "focusBorder": "#36b2d4",
    
    "quickInput.background": "#232d38",
    "quickInput.foreground": "#e5ded6",
    "quickInputList.focusBackground": "#313f4e",
    "quickInputList.focusForeground": "#e5ded6",
    "pickerGroup.foreground": "#36b2d4",
    "pickerGroup.border": "#313f4e",
    
    "button.background": "#36b2d4",
    "button.foreground": "#141C24",
    "button.hoverBackground": "#59dcd8",
    
    "panel.background": "#13181e",
    "panel.border": "#13181e",
    "panelTitle.activeForeground": "#e5ded6",
    "panelTitle.activeBorder": "#36b2d4",
    "panelTitle.inactiveForeground": "#abb2bf",
    
    "terminal.background": "#13181e",
    "terminal.foreground": "#e5ded6",
    "editorPane.background": "#13181e",
    "terminal.ansiBlack": "#13181e",
    "terminal.ansiRed": "#d32c5d",
    "terminal.ansiGreen": "#7fdc59",
    "terminal.ansiYellow": "#dcb659",
    "terminal.ansiBlue": "#36b2d4",
    "terminal.ansiMagenta": "#b759dc",
    "terminal.ansiCyan": "#00DFB5",
    "terminal.ansiWhite": "#e5ded6",
    "terminal.ansiBrightBlack": "#415367",
    "terminal.ansiBrightRed": "#dc597f",
    "terminal.ansiBrightGreen": "#7fdc59",
    "terminal.ansiBrightYellow": "#dcb659",
    "terminal.ansiBrightBlue": "#59dcd8",
    "terminal.ansiBrightMagenta": "#b759dc",
    "terminal.ansiBrightCyan": "#59dcd8",
    "terminal.ansiBrightWhite": "#e5ded6",
    
    "editorError.foreground": "#ee4d7f",
    "editorWarning.foreground": "#dc7759",
    "editorInfo.foreground": "#00DFB5",
    "editorHint.foreground": "#36b2d4",
    "editorError.background": "#00000000",
    "editorWarning.background": "#00000000",
    "editorInfo.background": "#00000000",
    
    "errorForeground": "#ee4d7f",
    "editorError.border": "#00000000",
    "inputValidation.errorBackground": "#00000000",
    "inputValidation.errorForeground": "#ee4d7f",
    "inputValidation.errorBorder": "#ee4d7f",
    
    "editorOverviewRuler.errorForeground": "#ee4d7f",
    "editorOverviewRuler.warningForeground": "#dc7759",
    "editorOverviewRuler.infoForeground": "#00DFB5",
    "editorOverviewRuler.modifiedForeground": "#dcb659",
    
    "problemsErrorIcon.foreground": "#ee4d7f",
    "problemsWarningIcon.foreground": "#dc7759",
    "problemsInfoIcon.foreground": "#00DFB5",
    
    "editorUnnecessaryCode.opacity": "#00000066",
    "editorUnnecessaryCode.border": "#00000000",
    
    "debugConsole.errorForeground": "#ee4d7f",
    "debugConsole.warningForeground": "#dc7759",
    "debugConsole.infoForeground": "#00DFB5",
    
    "notificationsErrorIcon.foreground": "#ee4d7f",
    "notificationsWarningIcon.foreground": "#dc7759",
    "notificationsInfoIcon.foreground": "#00DFB5",
    
    "editorGutter.addedBackground": "#00DFB5",
    "editorGutter.modifiedBackground": "#dcb659",
    "editorGutter.deletedBackground": "#ee4d7f",
    
    "diffEditor.insertedTextBackground": "#00DFB533",
    "diffEditor.removedTextBackground": "#ee4d7f33",
    
    "gitDecoration.modifiedResourceForeground": "#dcb659",
    "gitDecoration.deletedResourceForeground": "#ee4d7f",
    "gitDecoration.untrackedResourceForeground": "#00DFB5",
    "gitDecoration.ignoredResourceForeground": "#415367",
    "gitDecoration.conflictingResourceForeground": "#b759dc",
    
    "editorWidget.background": "#232d38",
    "editorWidget.foreground": "#e5ded6",
    "editorWidget.border": "#00000000",
    
    "editorSuggestWidget.background": "#232d38",
    "editorSuggestWidget.foreground": "#e5ded6",
    "editorSuggestWidget.highlightForeground": "#36b2d4",
    "editorSuggestWidget.selectedBackground": "#313f4e",
    "editorSuggestWidget.border": "#00000000",
    
    "editorHoverWidget.background": "#232d38",
    "editorHoverWidget.foreground": "#e5ded6",
    "editorHoverWidget.border": "#00000000",
    
    "scrollbar.shadow": "#00000030",
    "widget.shadow": "#00000030",
    "editorGroup.dropBackground": "#313f4e30"
  },
  "semanticHighlighting": true,
  "semanticTokenColors": {
    "variable.declaration": "#e5ded6",
    "variable.declaration.readonly": "#e5ded6",
    "property.declaration": "#e5ded6",
    "parameter.declaration": "#c6b8ad"
  },
  "tokenColors": [
    {
      "name": "Comment",
      "scope": ["comment", "punctuation.definition.comment"],
      "settings": {
        "foreground": "#abb2bf",
        "fontStyle": "italic"
      }
    },
    {
      "name": "String",
      "scope": ["string", "string.quoted"],
      "settings": {
        "foreground": "#00DFB5"
      }
    },
    {
      "name": "String Escape",
      "scope": ["constant.character.escape"],
      "settings": {
        "foreground": "#7fdc59",
        "fontStyle": "bold"
      }
    },
    {
      "name": "Number",
      "scope": ["constant.numeric"],
      "settings": {
        "foreground": "#36b2d4"
      }
    },
    {
      "name": "Built-in constant",
      "scope": ["constant.language", "constant.builtin"],
      "settings": {
        "foreground": "#00DFB5"
      }
    },
    {
      "name": "Constant",
      "scope": ["constant"],
      "settings": {
        "foreground": "#00DFB5"
      }
    },
    {
      "name": "Variable",
      "scope": ["variable", "variable.parameter"],
      "settings": {
        "foreground": "#c6b8ad"
      }
    },
    {
      "name": "Variable Declaration",
      "scope": [
        "variable.other.constant",
        "variable.other.readwrite",
        "meta.definition.variable",
        "entity.name.variable"
      ],
      "settings": {
        "foreground": "#e5ded6"
      }
    },
    {
      "name": "Member Variable",
      "scope": ["variable.member", "variable.other.member"],
      "settings": {
        "foreground": "#c6b8ad"
      }
    },
    {
      "name": "Keyword",
      "scope": ["keyword", "keyword.control", "keyword.control.import", "keyword.control.from"],
      "settings": {
        "foreground": "#dcb659",
        "fontStyle": "bold"
      }
    },
    {
      "name": "Keyword Directive",
      "scope": ["keyword.directive", "keyword.other.directive"],
      "settings": {
        "foreground": "#dcb659"
      }
    },
    {
      "name": "Operator",
      "scope": ["keyword.operator"],
      "settings": {
        "foreground": "#dc7759",
        "fontStyle": "bold"
      }
    },
    {
      "name": "Punctuation",
      "scope": ["punctuation", "punctuation.delimiter"],
      "settings": {
        "foreground": "#dc7759"
      }
    },
    {
      "name": "Function",
      "scope": ["entity.name.function", "meta.function-call"],
      "settings": {
        "foreground": "#59dcd8"
      }
    },
    {
      "name": "Built-in Function",
      "scope": ["support.function", "support.function.builtin"],
      "settings": {
        "foreground": "#59dcd8",
        "fontStyle": "bold"
      }
    },
    {
      "name": "Function Macro",
      "scope": ["entity.name.function.macro"],
      "settings": {
        "foreground": "#dc7759",
        "fontStyle": "bold"
      }
    },
    {
      "name": "Class, Type",
      "scope": [
        "entity.name.type",
        "entity.name.class",
        "support.class",
        "support.type"
      ],
      "settings": {
        "foreground": "#dc597f"
      }
    },
    {
      "name": "Built-in Type",
      "scope": ["support.type.builtin", "support.type.primitive"],
      "settings": {
        "foreground": "#d32c5d",
        "fontStyle": "bold"
      }
    },
    {
      "name": "Constructor",
      "scope": ["entity.name.function.constructor", "meta.constructor"],
      "settings": {
        "foreground": "#dc597f"
      }
    },
    {
      "name": "Attribute",
      "scope": ["entity.other.attribute-name"],
      "settings": {
        "foreground": "#dc7759"
      }
    },
    {
      "name": "Namespace",
      "scope": ["entity.name.namespace", "entity.name.module"],
      "settings": {
        "foreground": "#d32c5d"
      }
    },
    {
      "name": "Special",
      "scope": ["keyword.other.special-method"],
      "settings": {
        "foreground": "#7fdc59"
      }
    },
    {
      "name": "Import/Export",
      "scope": [
        "keyword.control.export",
        "keyword.control.import",
        "keyword.control.from",
        "keyword.control.as",
        "keyword.control.default",
        "keyword.control.type",
        "keyword.import",
        "keyword.export"
      ],
      "settings": {
        "foreground": "#dcb659",
        "fontStyle": "bold"
      }
    },
    {
      "name": "Storage Type",
      "scope": ["storage.type", "storage.modifier"],
      "settings": {
        "foreground": "#dcb659",
        "fontStyle": "bold"
      }
    },
    {
      "name": "Type Keyword",
      "scope": [
        "keyword.type",
        "keyword.other.type",
        "storage.type.type",
        "storage.type.interface",
        "storage.type.enum"
      ],
      "settings": {
        "foreground": "#dcb659",
        "fontStyle": "bold"
      }
    },
    {
      "name": "TypeScript specific",
      "scope": [
        "entity.name.type.module",
        "meta.import",
        "meta.export"
      ],
      "settings": {
        "foreground": "#dcb659",
        "fontStyle": "bold"
      }
    },
    {
      "name": "Label",
      "scope": ["entity.name.label"],
      "settings": {
        "foreground": "#36b2d4"
      }
    },
    {
      "name": "Tag",
      "scope": ["entity.name.tag", "meta.tag"],
      "settings": {
        "foreground": "#d32c5d"
      }
    },
    {
      "name": "Tag Attribute",
      "scope": ["meta.tag entity.other.attribute-name"],
      "settings": {
        "foreground": "#dc7759"
      }
    },
    {
      "name": "Invalid",
      "scope": ["invalid", "invalid.illegal"],
      "settings": {
        "foreground": "#ee4d7f"
      }
    },
    {
      "name": "Markup Heading",
      "scope": ["markup.heading", "entity.name.section"],
      "settings": {
        "foreground": "#36b2d4"
      }
    },
    {
      "name": "Markup List",
      "scope": ["markup.list"],
      "settings": {
        "foreground": "#e5ded6"
      }
    },
    {
      "name": "Markdown Text",
      "scope": [
        "text.html.markdown",
        "source.gfm",
        "text.html.markdown.gfm"
      ],
      "settings": {
        "foreground": "#e5ded6"
      }
    },
    {
      "name": "Markdown List Punctuation",
      "scope": [
        "punctuation.definition.list.begin.markdown",
        "punctuation.definition.list.markdown",
        "markup.list.unnumbered.markdown",
        "markup.list.numbered.markdown"
      ],
      "settings": {
        "foreground": "#abb2bf"
      }
    },
    {
      "name": "Markup Bold",
      "scope": ["markup.bold"],
      "settings": {
        "foreground": "#dcb659",
        "fontStyle": "bold"
      }
    },
    {
      "name": "Markup Italic",
      "scope": ["markup.italic"],
      "settings": {
        "foreground": "#b759dc",
        "fontStyle": "italic"
      }
    },
    {
      "name": "Markup Link",
      "scope": ["markup.underline.link"],
      "settings": {
        "foreground": "#dcb659",
        "fontStyle": "underline"
      }
    },
    {
      "name": "Markup Link Text",
      "scope": ["string.other.link"],
      "settings": {
        "foreground": "#d32c5d"
      }
    },
    {
      "name": "Markup Quote",
      "scope": ["markup.quote"],
      "settings": {
        "foreground": "#00DFB5"
      }
    },
    {
      "name": "Markup Raw",
      "scope": ["markup.raw", "markup.inline.raw"],
      "settings": {
        "foreground": "#7fdc59"
      }
    },
    {
      "name": "Diff Added",
      "scope": ["markup.inserted", "meta.diff.header.to-file"],
      "settings": {
        "foreground": "#00DFB5"
      }
    },
    {
      "name": "Diff Modified",
      "scope": ["markup.changed"],
      "settings": {
        "foreground": "#dc7759"
      }
    },
    {
      "name": "Diff Deleted",
      "scope": ["markup.deleted", "meta.diff.header.from-file"],
      "settings": {
        "foreground": "#dc597f"
      }
    },
    {
      "name": "JSX/TSX Text Content",
      "scope": [
        "meta.jsx.children",
        "meta.tsx.children",
        "JSXText",
        "text.html.basic",
        "meta.jsx.children.tsx",
        "meta.jsx.children.jsx"
      ],
      "settings": {
        "foreground": "#e5ded6"
      }
    }
  ]
}